{
	"info": {
		"_postman_id": "3db400ec-21b1-442d-b993-5cd088da9b4a",
		"name": "bloom",
		"schema": "https://schema.getpostman.com/json/collection/v2.1.0/collection.json",
		"_exporter_id": "25731435"
	},
	"item": [
		{
			"name": "wine",
			"item": [
				{
					"name": "get all wines",
					"request": {
						"auth": {
							"type": "bearer",
							"bearer": [
								{
									"key": "token",
									"value": "",
									"type": "string"
								}
							]
						},
						"method": "GET",
						"header": [],
						"url": {
							"raw": "http://localhost:8081/api/wines",
							"protocol": "http",
							"host": [
								"localhost"
							],
							"port": "8081",
							"path": [
								"api",
								"wines"
							]
						}
					},
					"response": []
				},
				{
					"name": "get a wine by id",
					"request": {
						"method": "GET",
						"header": [],
						"url": {
							"raw": "http://localhost:8081/api/wines/1",
							"protocol": "http",
							"host": [
								"localhost"
							],
							"port": "8081",
							"path": [
								"api",
								"wines",
								"1"
							]
						}
					},
					"response": []
				},
				{
					"name": "get with params",
					"request": {
						"method": "GET",
						"header": [],
						"url": {
							"raw": "http://localhost:8081/api/wines/search",
							"protocol": "http",
							"host": [
								"localhost"
							],
							"port": "8081",
							"path": [
								"api",
								"wines",
								"search"
							],
							"query": [
								{
									"key": "title",
									"value": "old mates pinot noir",
									"disabled": true
								},
								{
									"key": "title",
									"value": "old",
									"disabled": true
								},
								{
									"key": "priceFrom",
									"value": "30",
									"disabled": true
								},
								{
									"key": "priceTo",
									"value": "40",
									"disabled": true
								},
								{
									"key": "alcohol",
									"value": "12.0",
									"disabled": true
								},
								{
									"key": "variety",
									"value": "ORANGE",
									"disabled": true
								},
								{
									"key": "variety",
									"value": "ROSE",
									"disabled": true
								},
								{
									"key": "value",
									"value": "NATURAL",
									"disabled": true
								},
								{
									"key": "value",
									"value": "NON_ORGANIC",
									"disabled": true
								},
								{
									"key": "vintageFrom",
									"value": "2021",
									"disabled": true
								},
								{
									"key": "vintageTo",
									"value": "2023",
									"disabled": true
								},
								{
									"key": "grape",
									"value": "syraH",
									"disabled": true
								},
								{
									"key": "region",
									"value": "australiA",
									"disabled": true
								}
							]
						}
					},
					"response": []
				}
			]
		},
		{
			"name": "shopping cart",
			"item": [
				{
					"name": "add item to sh. cart",
					"request": {
						"auth": {
							"type": "bearer",
							"bearer": [
								{
									"key": "token",
									"value": "",
									"type": "string"
								}
							]
						},
						"method": "POST",
						"header": [],
						"body": {
							"mode": "raw",
							"raw": "{\n  \"wineId\": 1,\n  \"quantity\": 51\n}",
							"options": {
								"raw": {
									"language": "json"
								}
							}
						},
						"url": {
							"raw": "http://localhost:8081/api/cart",
							"protocol": "http",
							"host": [
								"localhost"
							],
							"port": "8081",
							"path": [
								"api",
								"cart"
							]
						}
					},
					"response": []
				},
				{
					"name": "get items shopping cart",
					"request": {
						"auth": {
							"type": "bearer",
							"bearer": [
								{
									"key": "token",
									"value": "",
									"type": "string"
								}
							]
						},
						"method": "GET",
						"header": [],
						"url": {
							"raw": "http://localhost:8081/api/cart",
							"protocol": "http",
							"host": [
								"localhost"
							],
							"port": "8081",
							"path": [
								"api",
								"cart"
							]
						}
					},
					"response": []
				},
				{
					"name": "update cart item in sh. cart",
					"request": {
						"auth": {
							"type": "bearer",
							"bearer": [
								{
									"key": "token",
									"value": "",
									"type": "string"
								}
							]
						},
						"method": "PUT",
						"header": [],
						"body": {
							"mode": "raw",
							"raw": "{\n    \"quantity\" : 77\n}",
							"options": {
								"raw": {
									"language": "json"
								}
							}
						},
						"url": {
							"raw": "http://localhost:8081/api/cart/items/4",
							"protocol": "http",
							"host": [
								"localhost"
							],
							"port": "8081",
							"path": [
								"api",
								"cart",
								"items",
								"4"
							]
						}
					},
					"response": []
				},
				{
					"name": "delete cart item from sh. cart",
					"request": {
						"auth": {
							"type": "bearer",
							"bearer": [
								{
									"key": "token",
									"value": "eyJhbGciOiJIUzUxMiJ9.eyJzdWIiOiIxY2NiOTUwZC1iZjFjLTRiYmYtOGJiNi04NzgxMDY4NmI2MzIifQ.gQVKeGof2JSYTaGfIWq_HMYy8w3bpFWGw2Z9JiM9EsSVQ-D1-F6w3cgVdeoZbHySVYmQxbH3MUdx6WIY330aFQ",
									"type": "string"
								}
							]
						},
						"method": "DELETE",
						"header": [],
						"url": {
							"raw": "http://localhost:8080/api/cart/9",
							"protocol": "http",
							"host": [
								"localhost"
							],
							"port": "8080",
							"path": [
								"api",
								"cart",
								"9"
							]
						}
					},
					"response": []
				}
			]
		},
		{
			"name": "auth",
			"item": [
				{
					"name": "register new user",
					"request": {
						"auth": {
							"type": "bearer",
							"bearer": [
								{
									"key": "token",
									"value": "",
									"type": "string"
								}
							]
						},
						"method": "POST",
						"header": [],
						"url": {
							"raw": "http://localhost:8081/api/auth/registration",
							"protocol": "http",
							"host": [
								"localhost"
							],
							"port": "8081",
							"path": [
								"api",
								"auth",
								"registration"
							]
						}
					},
					"response": []
				}
			]
		},
		{
			"name": "favorite item",
			"item": [
				{
					"name": "add favorite item",
					"request": {
						"auth": {
							"type": "bearer",
							"bearer": [
								{
									"key": "token",
									"value": "",
									"type": "string"
								}
							]
						},
						"method": "POST",
						"header": [],
						"body": {
							"mode": "raw",
							"raw": "{\n    \"wineId\" : 3\n}",
							"options": {
								"raw": {
									"language": "json"
								}
							}
						},
						"url": {
							"raw": "http://localhost:8081/api/favorites/add",
							"protocol": "http",
							"host": [
								"localhost"
							],
							"port": "8081",
							"path": [
								"api",
								"favorites",
								"add"
							]
						}
					},
					"response": []
				},
				{
					"name": "get all favorite user`s wines",
					"request": {
						"auth": {
							"type": "bearer",
							"bearer": [
								{
									"key": "token",
									"value": "",
									"type": "string"
								}
							]
						},
						"method": "GET",
						"header": [],
						"url": {
							"raw": "http://localhost:8081/api/favorites/all",
							"protocol": "http",
							"host": [
								"localhost"
							],
							"port": "8081",
							"path": [
								"api",
								"favorites",
								"all"
							]
						}
					},
					"response": []
				},
				{
					"name": "delete favorite item",
					"request": {
						"auth": {
							"type": "bearer",
							"bearer": [
								{
									"key": "token",
									"value": "",
									"type": "string"
								}
							]
						},
						"method": "DELETE",
						"header": [],
						"url": {
							"raw": "http://localhost:8081/api/favorites/2",
							"protocol": "http",
							"host": [
								"localhost"
							],
							"port": "8081",
							"path": [
								"api",
								"favorites",
								"2"
							]
						}
					},
					"response": []
				}
			]
		}
	]
}